restapicall/__init__.py
restapicall/api.py
restapicall/utils.py
tests/__init__.py
tests/test_api.py
tests/test_utils.py
RestApiCall-1.0.0.dist-info/LICENSE
RestApiCall-1.0.0.dist-info/METADATA
RestApiCall-1.0.0.dist-info/WHEEL
RestApiCall-1.0.0.dist-info/top_level.txt
RestApiCall-1.0.0.dist-info/RECORD
