Metadata-Version: 2.1
Name: RestApiCall
Version: 1.0.0
Summary: This python library is a REST API Call which generates REST URLs using attributes.
Home-page: https://github.com/oloc/restapicall
Author: Olivier Locard
Classifier: Intended Audience :: Developers
Classifier: Programming Language :: Python :: 3
Classifier: Programming Language :: Python :: 3.4
Classifier: Programming Language :: Python :: 3.5
Classifier: Programming Language :: Python :: 3.6
Classifier: Programming Language :: Python :: 3.7
Classifier: License :: OSI Approved :: ISC License (ISCL)
License-File: LICENSE
